summarize_cross_validation_score/__init__.py
summarize_cross_validation_score/summarize_cross_validation_score.py
summarize_cross_validation_score-0.1.0.dist-info/LICENSE
summarize_cross_validation_score-0.1.0.dist-info/WHEEL
summarize_cross_validation_score-0.1.0.dist-info/METADATA
summarize_cross_validation_score-0.1.0.dist-info/RECORD
